[
  {
    "channel_title": "AI MUSIC MATRIX",
    "channel_id": "UC4eEg9prJU6ApDrfsRwV1bw",
    "channel_url": "https://youtube.com/channel/UC4eEg9prJU6ApDrfsRwV1bw",
    "subscribers": 117000,
    "video_count": 72
  },
  {
    "channel_title": "AI Music",
    "channel_id": "UCFNy0ERBB7aGPvxmu_ApyOQ",
    "channel_url": "https://youtube.com/channel/UCFNy0ERBB7aGPvxmu_ApyOQ",
    "subscribers": 1470,
    "video_count": 27
  },
  {
    "channel_title": "Ai-Music Jam",
    "channel_id": "UCLOKFcvu3IuhRBKl0-hlJrA",
    "channel_url": "https://youtube.com/channel/UCLOKFcvu3IuhRBKl0-hlJrA",
    "subscribers": 19500,
    "video_count": 388
  },
  {
    "channel_title": " AI music world By Krish ",
    "channel_id": "UCsyGihVIvslvhggE6ghN8Sg",
    "channel_url": "https://youtube.com/channel/UCsyGihVIvslvhggE6ghN8Sg",
    "subscribers": 62,
    "video_count": 14
  },
  {
    "channel_title": "Abhi Ai music",
    "channel_id": "UCcsxdSOutjbDT9-NdwzD4Ow",
    "channel_url": "https://youtube.com/channel/UCcsxdSOutjbDT9-NdwzD4Ow",
    "subscribers": 117,
    "video_count": 15
  },
  {
    "channel_title": "AI MUSIC WALLAH ",
    "channel_id": "UCMI8OJuqI2_CbmpulZyMq-A",
    "channel_url": "https://youtube.com/channel/UCMI8OJuqI2_CbmpulZyMq-A",
    "subscribers": 25,
    "video_count": 10
  },
  {
    "channel_title": "Ai Music TV",
    "channel_id": "UCC_WCeGFQKagiMFF3zAgK5A",
    "channel_url": "https://youtube.com/channel/UCC_WCeGFQKagiMFF3zAgK5A",
    "subscribers": 1450,
    "video_count": 99
  },
  {
    "channel_title": "SOUNDRAW - AI Music Generator",
    "channel_id": "UC6dgJ7YnS_cdly_RowbWP5A",
    "channel_url": "https://youtube.com/channel/UC6dgJ7YnS_cdly_RowbWP5A",
    "subscribers": 4390,
    "video_count": 54
  },
  {
    "channel_title": "AI Hitmakers - The Best AI-Generated Music",
    "channel_id": "UCovPavXGolNI6nOfIPC-bow",
    "channel_url": "https://youtube.com/channel/UCovPavXGolNI6nOfIPC-bow",
    "subscribers": 475,
    "video_count": 47
  },
  {
    "channel_title": "NEURAL MUSIC MIXES",
    "channel_id": "UC04lFITyKWFKAsG2QUbxebw",
    "channel_url": "https://youtube.com/channel/UC04lFITyKWFKAsG2QUbxebw",
    "subscribers": 254,
    "video_count": 45
  },
  {
    "channel_title": "Neural Music",
    "channel_id": "UCLDrA_eXYOzrBUPQ6CfC8Lg",
    "channel_url": "https://youtube.com/channel/UCLDrA_eXYOzrBUPQ6CfC8Lg",
    "subscribers": 71,
    "video_count": 11
  },
  {
    "channel_title": "Neural Music Notes",
    "channel_id": "UChnhLu5XDdb6cz1DOfHBKcQ",
    "channel_url": "https://youtube.com/channel/UChnhLu5XDdb6cz1DOfHBKcQ",
    "subscribers": 9,
    "video_count": 212
  },
  {
    "channel_title": "Neural Music",
    "channel_id": "UC84uGQ7g7xnrfEY3Mesyi2g",
    "channel_url": "https://youtube.com/channel/UC84uGQ7g7xnrfEY3Mesyi2g",
    "subscribers": 4,
    "video_count": 23
  },
  {
    "channel_title": "Neural Music Beats",
    "channel_id": "UCNpHWcFgZdLQPTzE-1CD1kQ",
    "channel_url": "https://youtube.com/channel/UCNpHWcFgZdLQPTzE-1CD1kQ",
    "subscribers": 137,
    "video_count": 120
  },
  {
    "channel_title": "Neural Notes",
    "channel_id": "UC1MI6XSbla3YdOyAh6b6eiw",
    "channel_url": "https://youtube.com/channel/UC1MI6XSbla3YdOyAh6b6eiw",
    "subscribers": 3870,
    "video_count": 185
  },
  {
    "channel_title": "AI-POP",
    "channel_id": "UCAQSJSC8eIOTDyfb-VhdpTA",
    "channel_url": "https://youtube.com/channel/UCAQSJSC8eIOTDyfb-VhdpTA",
    "subscribers": 49,
    "video_count": 68
  },
  {
    "channel_title": "AI Composer",
    "channel_id": "UC1QaY2MnWBMQQUo6vSm33fg",
    "channel_url": "https://youtube.com/channel/UC1QaY2MnWBMQQUo6vSm33fg",
    "subscribers": 11,
    "video_count": 12
  },
  {
    "channel_title": "\ud83d\udc7e AI Composer \ud83d\udc7e",
    "channel_id": "UCkhsQbEttH8IjMjgH2EQi6A",
    "channel_url": "https://youtube.com/channel/UCkhsQbEttH8IjMjgH2EQi6A",
    "subscribers": 0,
    "video_count": 29
  },
  {
    "channel_title": "Ai Composer",
    "channel_id": "UCsVgZeTi3uYKguCKd86M3bA",
    "channel_url": "https://youtube.com/channel/UCsVgZeTi3uYKguCKd86M3bA",
    "subscribers": 27,
    "video_count": 49
  }
]